src/salesforce/__init__.py
src/salesforce/server.py
orange_mcp_salesforce_connector-0.1.3.dist-info/METADATA
orange_mcp_salesforce_connector-0.1.3.dist-info/WHEEL
orange_mcp_salesforce_connector-0.1.3.dist-info/entry_points.txt
orange_mcp_salesforce_connector-0.1.3.dist-info/RECORD
