Metadata-Version: 2.4
Name: orange-mcp-salesforce-connector
Version: 0.1.3
Summary: A Model Context Protocol (MCP) server implementation for Salesforce integration
Project-URL: Homepage, https://github.com/smn2gnt/MCP-Salesforce
Author-email: Suman G <suman.gunaganti@gmail.com>
License: MIT
Keywords: llm,mcp,salesforce
Requires-Python: >=3.10
Requires-Dist: mcp
Requires-Dist: python-dotenv
Requires-Dist: simple-salesforce
